evoml_preprocessor/__init__.py
evoml_preprocessor/cli.py
evoml_preprocessor/py.typed
evoml_preprocessor/data/nlp_utils/Emoticon_Dict.p
evoml_preprocessor/data/nlp_utils/slang_words.txt
evoml_preprocessor/decomposition/__init__.py
evoml_preprocessor/decomposition/dimensionality_reduction.py
evoml_preprocessor/decomposition/enum.py
evoml_preprocessor/nlp/__init__.py
evoml_preprocessor/nlp/enum.py
evoml_preprocessor/nlp/huggingface.py
evoml_preprocessor/nlp/nlp_preprocessing.py
evoml_preprocessor/nlp/nlp_utils.py
evoml_preprocessor/nlp/patterns.py
evoml_preprocessor/preprocess/__init__.py
evoml_preprocessor/preprocess/preprocessor.py
evoml_preprocessor/preprocess/generator/__init__.py
evoml_preprocessor/preprocess/generator/feature_generation.py
evoml_preprocessor/preprocess/generator/models.py
evoml_preprocessor/preprocess/generator/node.py
evoml_preprocessor/preprocess/generator/operations.py
evoml_preprocessor/preprocess/generator/pool.py
evoml_preprocessor/preprocess/generator/report_builder.py
evoml_preprocessor/preprocess/generator/util.py
evoml_preprocessor/preprocess/generator/builder/__init__.py
evoml_preprocessor/preprocess/generator/builder/_base.py
evoml_preprocessor/preprocess/generator/builder/genetic.py
evoml_preprocessor/preprocess/generator/builder/grow_all.py
evoml_preprocessor/preprocess/generator/builder/grow_sampled.py
evoml_preprocessor/preprocess/generator/builder/polynomial.py
evoml_preprocessor/preprocess/generator/scorer/__init__.py
evoml_preprocessor/preprocess/generator/scorer/_base.py
evoml_preprocessor/preprocess/generator/scorer/lasso.py
evoml_preprocessor/preprocess/generator/scorer/lightgbm.py
evoml_preprocessor/preprocess/generator/scorer/mrmr.py
evoml_preprocessor/preprocess/generator/scorer/mrmr_fast.py
evoml_preprocessor/preprocess/generator/scorer/qpfs.py
evoml_preprocessor/preprocess/handlers/__init__.py
evoml_preprocessor/preprocess/handlers/factory.py
evoml_preprocessor/preprocess/handlers/utils.py
turintech_evoml_preprocessor-5.1.1.dist-info/LICENSE
turintech_evoml_preprocessor-5.1.1.dist-info/METADATA
turintech_evoml_preprocessor-5.1.1.dist-info/WHEEL
turintech_evoml_preprocessor-5.1.1.dist-info/top_level.txt
turintech_evoml_preprocessor-5.1.1.dist-info/RECORD
