Metadata-Version: 2.1
Name: turintech-evoml-preprocessor
Version: 5.1.1
Summary: Preprocess data.
Home-page: https://turintech.ai
Author: Turing Intelligence Technology
License: TURING INTELLIGENCE TECHNOLOGY LIMITED END-USER LICENCE
Keywords: turintech,evoml,preprocessor
Classifier: Development Status :: 5 - Production/Stable
Classifier: License :: Other/Proprietary License
Classifier: Programming Language :: Python :: 3.9
Classifier: Programming Language :: Python :: 3.10
Classifier: Programming Language :: Python :: 3.11
Requires-Python: >=3.9,<4
License-File: LICENSE
Requires-Dist: turintech-evoml-utils (<3.0.0,>=2.0.1)
Requires-Dist: turintech-evoml-api-models (<4.0.0,>=3.1.0)
Requires-Dist: numpy (<1.25.0,>=1.20.0)
Requires-Dist: pandas (<2.0.0,>=1.4.2)
Requires-Dist: joblib (<2.0.0,>=1.2.0)
Requires-Dist: scikit-learn (<1.7.0,>=1.5.0)
Requires-Dist: anytree (<3.0.0,>=2.8.0)
Requires-Dist: category-encoders (<2.7.0,>=2.6.0)
Requires-Dist: mlxtend (<1.0.0,>=0.21.0)
Requires-Dist: xxhash (<4.0.0,>=2.0.2)
Requires-Dist: scipy (<=2.0.0)
Requires-Dist: tqdm (<5.0.0,>=4.64.1)
Requires-Dist: cvxopt (<2.0.0,>=1.3.0)
Requires-Dist: sympy (<1.14,>=1.0)
Requires-Dist: typing-extensions (>=4.0.0)
Requires-Dist: lightgbm (<5.0.0,>=3.3.3)
Provides-Extra: all
Requires-Dist: transformers[torch] (<5.0.0,>=4.42.0) ; extra == 'all'
Requires-Dist: torch (<3.0.0,>=1.12.1) ; extra == 'all'
Requires-Dist: sacremoses (<1.0.0,>=0.0.53) ; extra == 'all'
Requires-Dist: optimum[onnxruntime] (>=1.19.0) ; extra == 'all'
Requires-Dist: onnxruntime (>=1.1.70) ; extra == 'all'
Requires-Dist: emot (<4.0,>=3.1) ; extra == 'all'
Requires-Dist: contractions (<1.0.0,>=0.1.73) ; extra == 'all'
Requires-Dist: autocorrect (<3.0.0,>=2.6.1) ; extra == 'all'
Requires-Dist: schwifty (~=2025.1.0) ; extra == 'all'
Requires-Dist: python-stdnum (~=1.20) ; extra == 'all'
Requires-Dist: transformers (<5.0.0,>=4.42.0) ; extra == 'all'
Requires-Dist: biopython (<1.86,>=1.79) ; extra == 'all'
Requires-Dist: turintech-evoml-utils (<3.0.0,>=2.0.1) ; extra == 'all'
Requires-Dist: turintech-evoml-api-models (<4.0.0,>=3.1.0) ; extra == 'all'
Requires-Dist: numpy (<1.25.0,>=1.20.0) ; extra == 'all'
Requires-Dist: pandas (<2.0.0,>=1.4.2) ; extra == 'all'
Requires-Dist: joblib (<2.0.0,>=1.2.0) ; extra == 'all'
Requires-Dist: scikit-learn (<1.7.0,>=1.5.0) ; extra == 'all'
Requires-Dist: anytree (<3.0.0,>=2.8.0) ; extra == 'all'
Requires-Dist: category-encoders (<2.7.0,>=2.6.0) ; extra == 'all'
Requires-Dist: mlxtend (<1.0.0,>=0.21.0) ; extra == 'all'
Requires-Dist: xxhash (<4.0.0,>=2.0.2) ; extra == 'all'
Requires-Dist: scipy (<=2.0.0) ; extra == 'all'
Requires-Dist: tqdm (<5.0.0,>=4.64.1) ; extra == 'all'
Requires-Dist: cvxopt (<2.0.0,>=1.3.0) ; extra == 'all'
Requires-Dist: sympy (<1.14,>=1.0) ; extra == 'all'
Requires-Dist: typing-extensions (>=4.0.0) ; extra == 'all'
Requires-Dist: lightgbm (<5.0.0,>=3.3.3) ; extra == 'all'
Provides-Extra: bankcode
Requires-Dist: schwifty (~=2025.1.0) ; extra == 'bankcode'
Provides-Extra: barcode
Requires-Dist: python-stdnum (~=1.20) ; extra == 'barcode'
Provides-Extra: proteinsequence
Requires-Dist: torch (<3.0.0,>=1.12.1) ; extra == 'proteinsequence'
Requires-Dist: transformers (<5.0.0,>=4.42.0) ; extra == 'proteinsequence'
Requires-Dist: sacremoses (<1.0.0,>=0.0.53) ; extra == 'proteinsequence'
Requires-Dist: optimum[onnxruntime] (>=1.19.0) ; extra == 'proteinsequence'
Requires-Dist: onnxruntime (>=1.1.70) ; extra == 'proteinsequence'
Requires-Dist: biopython (<1.86,>=1.79) ; extra == 'proteinsequence'
Provides-Extra: text
Requires-Dist: transformers[torch] (<5.0.0,>=4.42.0) ; extra == 'text'
Requires-Dist: torch (<3.0.0,>=1.12.1) ; extra == 'text'
Requires-Dist: sacremoses (<1.0.0,>=0.0.53) ; extra == 'text'
Requires-Dist: optimum[onnxruntime] (>=1.19.0) ; extra == 'text'
Requires-Dist: onnxruntime (>=1.1.70) ; extra == 'text'
Requires-Dist: emot (<4.0,>=3.1) ; extra == 'text'
Requires-Dist: contractions (<1.0.0,>=0.1.73) ; extra == 'text'
Requires-Dist: autocorrect (<3.0.0,>=2.6.1) ; extra == 'text'
